ppmenu/__init__.py
ppmenu/constants.py
ppmenu-0.1.1.dist-info/licenses/LICENSE
ppmenu-0.1.1.dist-info/METADATA
ppmenu-0.1.1.dist-info/WHEEL
ppmenu-0.1.1.dist-info/top_level.txt
ppmenu-0.1.1.dist-info/RECORD
