Metadata-Version: 2.4
Name: ppmenu
Version: 0.1.1
Summary: A pure Python terminal menu system with quick navigation and custom layouts.
Author-email: Sergey Samoylov <linews@yandex.ru>
License:                     GNU GENERAL PUBLIC LICENSE
Project-URL: Homepage, https://github.com/sergey-samoylov/ppmenu
Project-URL: Repository, https://github.com/sergey-samoylov/ppmenu
Project-URL: Issues, https://github.com/sergey-samoylov/ppmenu/issues
Classifier: Programming Language :: Python :: 3
Classifier: Programming Language :: Python :: 3.8
Classifier: Programming Language :: Python :: 3.9
Classifier: Programming Language :: Python :: 3.10
Classifier: Programming Language :: Python :: 3.11
Classifier: License :: OSI Approved :: GNU General Public License v3 (GPLv3)
Classifier: Operating System :: OS Independent
Requires-Python: >=3.8
License-File: LICENSE
Dynamic: license-file
